ctfi2/__init__.py
ctfi2/configuration.py
ctfi2/api/__init__.py
ctfi2/api/api.py
ctfi2/api/constants.py
ctfi2/cli/__init__.py
ctfi2/gui/CTFi2GUI.py
ctfi2/gui/__init__.py
ctfi2/gui/gui.py
ctfi2/gui/components/__init__.py
ctfi2/gui/components/challengewidget.py
ctfi2/gui/components/competitiontree.py
ctfi2/gui/components/componentfactory.py
ctfi2/gui/components/filewidget.py
ctfi2/gui/components/flagwidget.py
ctfi2/gui/components/hintwidget.py
ctfi2/gui/components/requirementwidget.py
ctfi2/gui/components/serverwidget.py
ctfi2/gui/components/titlewidget.py
ctfi2/gui/components/userimportwidget.py
ctfi2/gui/components/userwidget.py
ctfi2-1.5.4.data/scripts/ctfi2
ctfi2-1.5.4.dist-info/LICENSE
ctfi2-1.5.4.dist-info/METADATA
ctfi2-1.5.4.dist-info/WHEEL
ctfi2-1.5.4.dist-info/top_level.txt
ctfi2-1.5.4.dist-info/RECORD
