Metadata-Version: 2.1
Name: ctfi2
Version: 1.5.4
Summary: ctfi2 - CTFd Interface 2
Home-page: https://github.com/drpresq/ctfi2
Author: George
Author-email: drpresq@gmail.com
License: UNKNOWN
Platform: UNKNOWN
Classifier: Development Status :: 5 - Production/Stable
Classifier: Intended Audience :: Information Technology
Classifier: Intended Audience :: Science/Research
Classifier: License :: OSI Approved :: GNU General Public License v3 (GPLv3)
Classifier: Operating System :: OS Independent
Classifier: Programming Language :: Python :: 3.6
Classifier: Programming Language :: Python :: 3.7
Classifier: Programming Language :: Python :: 3.8
Classifier: Programming Language :: Python :: 3.9
Classifier: Programming Language :: Python :: 3.10
Classifier: Topic :: Utilities
License-File: LICENSE
Requires-Dist: requests (>=2.22.0)
Requires-Dist: PyQt5 (>=5.9.2)
Requires-Dist: simplejson (>=3.16.0)
Requires-Dist: setuptools (>=45.2.0)
